LICENSE
README.md
setup.py
hmedia/__init__.py
hmedia/views.py
hmedia.egg-info/PKG-INFO
hmedia.egg-info/SOURCES.txt
hmedia.egg-info/dependency_links.txt
hmedia.egg-info/requires.txt
hmedia.egg-info/top_level.txt