Metadata-Version: 2.1
Name: hmedia
Version: 1.0.0
Summary: Django本地存储的图片，前端调用通过参数生成缩略图与格式转换
Home-page: https://github.com/spirits001/python-HMedia
Author: 代码厨子
Author-email: 15755153@qq.com
Classifier: Programming Language :: Python :: 3
Classifier: License :: OSI Approved :: MIT License
Classifier: Operating System :: OS Independent
Requires-Python: >=3
License-File: LICENSE
Requires-Dist: django
Requires-Dist: pillow
